setup.py
src/fb303/FacebookBase.py
src/fb303/FacebookService.py
src/fb303/__init__.py
src/fb303/constants.py
src/fb303/ttypes.py
src/fb303_scripts/__init__.py
src/fb303_scripts/fb303_simple_mgmt.py
src/hive_metastore/ThriftHiveMetastore.py
src/hive_metastore/__init__.py
src/hive_metastore/constants.py
src/hive_metastore/ttypes.py
src/hive_serde/__init__.py
src/hive_serde/constants.py
src/hive_serde/ttypes.py
src/hive_service/ThriftHive.py
src/hive_service/__init__.py
src/hive_service/constants.py
src/hive_service/ttypes.py
src/hive_thrift_py.egg-info/PKG-INFO
src/hive_thrift_py.egg-info/SOURCES.txt
src/hive_thrift_py.egg-info/dependency_links.txt
src/hive_thrift_py.egg-info/top_level.txt
src/hive_thrift_py.egg-info/zip-safe
src/queryplan/__init__.py
src/queryplan/constants.py
src/queryplan/ttypes.py
src/thrift/TSCons.py
src/thrift/Thrift.py
src/thrift/__init__.py
src/thrift/protocol/TBinaryProtocol.py
src/thrift/protocol/TProtocol.py
src/thrift/protocol/__init__.py
src/thrift/reflection/__init__.py
src/thrift/reflection/limited/__init__.py
src/thrift/reflection/limited/constants.py
src/thrift/reflection/limited/ttypes.py
src/thrift/server/THttpServer.py
src/thrift/server/TNonblockingServer.py
src/thrift/server/TServer.py
src/thrift/server/__init__.py
src/thrift/transport/THttpClient.py
src/thrift/transport/TSocket.py
src/thrift/transport/TTransport.py
src/thrift/transport/TTwisted.py
src/thrift/transport/__init__.py