Metadata-Version: 1.0
Name: hive-thrift-py
Version: 0.0.1
Summary: Hive Python Thrift Libs
Home-page: http://hive.apache.org
Author: Youngwoo Kim
Author-email: warwithin@gmail.com
License: Apache License
Keywords: hive hadoop thrift
Platform: UNKNOWN
